ormagic/__init__.py
ormagic/clients/__init__.py
ormagic/clients/client.py
ormagic/clients/postgres.py
ormagic/clients/sqlite.py
ormagic/field_utils.py
ormagic/fields.py
ormagic/models.py
ormagic/query.py
ormagic/settings.py
ormagic/table_manager.py
ormagic/transactions.py
ormagic-0.16.1.dist-info/LICENSE
ormagic-0.16.1.dist-info/METADATA
ormagic-0.16.1.dist-info/WHEEL
ormagic-0.16.1.dist-info/RECORD
