Metadata-Version: 2.3
Name: ORMagic
Version: 0.16.1
Summary: ORMagic is a simple, fast, and lightweight ORM for Python, built on top of Pydantic.
License: MIT
Keywords: sql,orm,database,sqlite,db,sqlite3,pydantic,fastapi,postgresql,psycopg2,postgres
Author: SpaceShaman
Author-email: spaceshaman@tuta.io
Requires-Python: >=3.11,<4.0
Classifier: Framework :: Pydantic
Classifier: Framework :: Pydantic :: 2
Classifier: License :: OSI Approved :: MIT License
Classifier: Programming Language :: Python :: 3
Classifier: Programming Language :: Python :: 3.11
Classifier: Programming Language :: Python :: 3.12
Classifier: Programming Language :: Python :: 3.13
Classifier: Programming Language :: SQL
Provides-Extra: postgres
Requires-Dist: psycopg2-binary (>=2.9.10,<3.0.0) ; extra == "postgres"
Requires-Dist: pydantic (>=2.8.2,<3.0.0)
Project-URL: Documentation, https://spaceshaman.github.io/ORMagic/
Project-URL: Homepage, https://spaceshaman.github.io/ORMagic/
Project-URL: Repository, https://github.com/SpaceShaman/ORMagic
